cloudrail/cli/__init__.py
cloudrail/cli/_version.py
cloudrail/cli/cli.py
cloudrail/cli/cli_configuration.py
cloudrail/cli/cli_execution_reporter.py
cloudrail/cli/cloudrail_multi_command.py
cloudrail/cli/commands_utils.py
cloudrail/cli/custom_click_options.py
cloudrail/cli/error_messages.py
cloudrail/cli/exit_codes.py
cloudrail/cli/exit_hooks.py
cloudrail/cli/output_format.py
cloudrail/cli/spinner_wrapper.py
cloudrail/cli/api_client/__init__.py
cloudrail/cli/api_client/cloudrail_api_client.py
cloudrail/cli/api_client/external_api_client.py
cloudrail/cli/api_client/contract/__init__.py
cloudrail/cli/api_client/contract/cloudrail_api_response.py
cloudrail/cli/commands/__init__.py
cloudrail/cli/commands/cloud_account.py
cloudrail/cli/commands/config.py
cloudrail/cli/commands/generate_filtered_cfn_template.py
cloudrail/cli/commands/generate_filtered_plan.py
cloudrail/cli/commands/run.py
cloudrail/cli/result_formatter/__init__.py
cloudrail/cli/result_formatter/base_formatter.py
cloudrail/cli/result_formatter/json_formatter.py
cloudrail/cli/result_formatter/json_gitlab_sast_formatter.py
cloudrail/cli/result_formatter/junit_formatter.py
cloudrail/cli/result_formatter/sarif_formatter.py
cloudrail/cli/result_formatter/text_formatter.py
cloudrail/cli/service/__init__.py
cloudrail/cli/service/base_cloudformation_command_parameters.py
cloudrail/cli/service/checkov_executor.py
cloudrail/cli/service/cloud_account_command_service.py
cloudrail/cli/service/cloudrail_cli_service.py
cloudrail/cli/service/command_parameters.py
cloudrail/cli/service/command_service.py
cloudrail/cli/service/generate_cloudformation_template_service.py
cloudrail/cli/service/service_response.py
cloudrail/cli/service/service_response_status.py
cloudrail/cli/service/evaluation_run_command/__init__.py
cloudrail/cli/service/evaluation_run_command/base_run_command_service.py
cloudrail/cli/service/evaluation_run_command/cloudformation_run_command_service.py
cloudrail-1.3.836.dist-info/METADATA
cloudrail-1.3.836.dist-info/WHEEL
cloudrail-1.3.836.dist-info/entry_points.txt
cloudrail-1.3.836.dist-info/top_level.txt
cloudrail-1.3.836.dist-info/RECORD
